authzee/__init__.py
authzee/authzee.py
authzee/authzee_sync.py
authzee/backend_locality.py
authzee/exceptions.py
authzee/grant.py
authzee/grant_effect.py
authzee/grants_page.py
authzee/logging_config.py
authzee/loop.py
authzee/page_refs_page.py
authzee/raw_grants_page.py
authzee/resource_action.py
authzee/resource_authz.py
authzee/compute/__init__.py
authzee/compute/compute_backend.py
authzee/compute/general.py
authzee/compute/main_process_compute.py
authzee/compute/multiprocess_compute.py
authzee/compute/shared_mem_event.py
authzee/compute/threaded_compute.py
authzee/storage/__init__.py
authzee/storage/memory_storage.py
authzee/storage/sql_storage.py
authzee/storage/sql_storage_models.py
authzee/storage/storage_backend.py
authzee-0.1.0a3.dist-info/METADATA
authzee-0.1.0a3.dist-info/WHEEL
authzee-0.1.0a3.dist-info/top_level.txt
authzee-0.1.0a3.dist-info/RECORD
