Metadata-Version: 2.1
Name: authzee
Version: 0.1.0a3
Summary: Authorization framework that uses a querying grant and revoke system.
Home-page: https://github.com/btemplep/authzee
Author: Brandon Temple Paul
Author-email: btemplepgit@gmail.com
License: MIT
Project-URL: Repository, https://github.com/btemplep/authzee
Keywords: auth,authz,authorization,framework
Classifier: Development Status :: 3 - Alpha
Classifier: License :: OSI Approved :: MIT License
Classifier: Natural Language :: English
Classifier: Operating System :: POSIX :: Linux
Classifier: Operating System :: Unix
Classifier: Programming Language :: Python :: 3
Classifier: Programming Language :: Python :: 3 :: Only
Classifier: Programming Language :: Python :: 3.8
Classifier: Programming Language :: Python :: 3.9
Classifier: Programming Language :: Python :: 3.10
Classifier: Programming Language :: Python :: 3.11
Classifier: Programming Language :: Python :: 3.12
Classifier: Programming Language :: Python :: Implementation :: CPython
Classifier: Topic :: Software Development :: Libraries :: Python Modules
Classifier: Topic :: Internet
Requires-Dist: loguru
Requires-Dist: jmespath
Requires-Dist: pydantic ~=2.0
Provides-Extra: all
Requires-Dist: authzee[sql] ; extra == 'all'
Provides-Extra: dev
Requires-Dist: build ; extra == 'dev'
Requires-Dist: coverage ; extra == 'dev'
Requires-Dist: nox ; extra == 'dev'
Requires-Dist: piccolo-theme ; extra == 'dev'
Requires-Dist: pytest ; extra == 'dev'
Requires-Dist: pytest-cov ; extra == 'dev'
Requires-Dist: sphinx ; extra == 'dev'
Requires-Dist: twine ; extra == 'dev'
Provides-Extra: sql
Requires-Dist: SQLAlchemy ~=2.0 ; extra == 'sql'
